getopenpay/__init__.py
getopenpay/api_client.py
getopenpay/api_response.py
getopenpay/client.py
getopenpay/configuration.py
getopenpay/exceptions.py
getopenpay/py.typed
getopenpay/rest.py
getopenpay/api/__init__.py
getopenpay/api/billing_meter_event_adjustments_api.py
getopenpay/api/billing_meter_events_api.py
getopenpay/api/billing_meters_api.py
getopenpay/api/billing_portal_api.py
getopenpay/api/charges_api.py
getopenpay/api/checkout_api.py
getopenpay/api/coupons_api.py
getopenpay/api/credit_notes_api.py
getopenpay/api/customers_api.py
getopenpay/api/disputes_api.py
getopenpay/api/events_api.py
getopenpay/api/invoice_items_api.py
getopenpay/api/invoices_api.py
getopenpay/api/payment_intents_api.py
getopenpay/api/payment_links_api.py
getopenpay/api/payment_methods_api.py
getopenpay/api/payment_routes_api.py
getopenpay/api/prices_api.py
getopenpay/api/product_bundles_api.py
getopenpay/api/product_family_api.py
getopenpay/api/products_api.py
getopenpay/api/promotion_codes_api.py
getopenpay/api/refunds_api.py
getopenpay/api/signup_answers_api.py
getopenpay/api/subscription_items_api.py
getopenpay/api/subscriptions_api.py
getopenpay/api/tax_integrations_api.py
getopenpay/models/__init__.py
getopenpay/models/active_sub_response.py
getopenpay/models/add_comment_request.py
getopenpay/models/attach_payment_method_request.py
getopenpay/models/authorize_payment_method_request.py
getopenpay/models/billing_meter_adjustment_type.py
getopenpay/models/billing_meter_aggregation_formula.py
getopenpay/models/billing_meter_event_adjustment_external.py
getopenpay/models/billing_meter_event_adjustment_status.py
getopenpay/models/billing_meter_event_external.py
getopenpay/models/billing_meter_event_status.py
getopenpay/models/billing_meter_external.py
getopenpay/models/billing_meter_query_params.py
getopenpay/models/billing_meter_summary.py
getopenpay/models/billing_reason_enum.py
getopenpay/models/billing_scheme_enum.py
getopenpay/models/boolean_config_field.py
getopenpay-0.0.30.dist-info/METADATA
getopenpay-0.0.30.dist-info/WHEEL
getopenpay-0.0.30.dist-info/top_level.txt
getopenpay-0.0.30.dist-info/RECORD
